ruby/__init__.py
ruby/translator.py
ruby/utils/__init__.py
ruby/utils/misc.py
ruby/utils/tree_manipulation.py
ruby-0.0.2.dist-info/LICENSE
ruby-0.0.2.dist-info/METADATA
ruby-0.0.2.dist-info/WHEEL
ruby-0.0.2.dist-info/top_level.txt
ruby-0.0.2.dist-info/RECORD
