Metadata-Version: 2.1
Name: ruby
Version: 0.0.2
Summary: RUBY: Universal Rule-based Machine Translation NLP Toolkit
Home-page: https://github.com/nlp-ruby/ruby
Author: Truong-Phat Nguyen
Author-email: me@patrickphat.com
License: UNKNOWN
Platform: UNKNOWN
Classifier: Programming Language :: Python :: 3
Classifier: License :: OSI Approved :: MIT License
Classifier: Operating System :: OS Independent
Requires-Python: >3.6
Provides-Extra: dev
